meridian_crossing/__init__.py
meridian_crossing/cli.py
meridian_crossing/utils.py
meridian_crossing-0.2.1.dist-info/METADATA
meridian_crossing-0.2.1.dist-info/WHEEL
meridian_crossing-0.2.1.dist-info/entry_points.txt
meridian_crossing-0.2.1.dist-info/licenses/LICENSE
meridian_crossing-0.2.1.dist-info/RECORD
