Metadata-Version: 2.4
Name: meridian_crossing
Version: 0.2.1
Author-email: Taka <amano.takahisa@gmail.com>
License-File: LICENSE
Requires-Python: >=3.11
Requires-Dist: click<9,>=8.3.0
Requires-Dist: geopandas<2,>=1.1.1
Requires-Dist: shapely<3,>=2.1.2
